optipy/__init__.py
optipy/_get_version.py
optipy/_get_version_list.py
optipy-2.0.2.dist-info/LICENSE
optipy-2.0.2.dist-info/METADATA
optipy-2.0.2.dist-info/WHEEL
optipy-2.0.2.dist-info/top_level.txt
optipy-2.0.2.dist-info/RECORD
