Metadata-Version: 2.1
Name: optipy
Version: 2.0.2
Summary: Web Scraping API for getting Optifine VersionsList/Versions/Download-URL.
Home-page: https://github.com/GoodDay360/OptiPy
Author: GoodDay360
Author-email: istartgame31@gmail.com
License: MIT
Keywords: optifine,api,optifine_api
Classifier: Development Status :: 5 - Production/Stable
Classifier: Intended Audience :: Information Technology
Classifier: Operating System :: OS Independent
Classifier: License :: OSI Approved :: MIT License
Classifier: Programming Language :: Python :: 3
Requires-Python: >=3.6
License-File: LICENSE
Requires-Dist: beautifulsoup4 ==4.12.2
Requires-Dist: certifi ==2023.7.22
Requires-Dist: charset-normalizer ==3.2.0
Requires-Dist: idna ==3.4
Requires-Dist: requests ==2.31.0
Requires-Dist: soupsieve ==2.5
Requires-Dist: urllib3 ==2.0.5
